aiogram_samples/__init__.py
aiogram_samples/cli.py
aiogram_samples/templates.py
aiogram_samples-0.2.4.dist-info/METADATA
aiogram_samples-0.2.4.dist-info/WHEEL
aiogram_samples-0.2.4.dist-info/entry_points.txt
aiogram_samples-0.2.4.dist-info/top_level.txt
aiogram_samples-0.2.4.dist-info/RECORD
