Metadata-Version: 2.4
Name: aiogram_samples
Version: 0.2.4
Summary: Генератор шаблонов для aiogram обработчиков и начала проекта
Home-page: https://github.com/lumpButton/aiogram_samples
Author: Lump
Author-email: igropritegatel11@gmail.com
Classifier: Programming Language :: Python :: 3
Classifier: License :: OSI Approved :: MIT License
Classifier: Operating System :: OS Independent
Requires-Python: >=3.7
Dynamic: author
Dynamic: author-email
Dynamic: classifier
Dynamic: description
Dynamic: description-content-type
Dynamic: home-page
Dynamic: requires-python
Dynamic: summary
